{
  "StartAt": "RegisterIncident",
  "Comment": "Developing with AWS Step Functions Demo",
  "States": {
    "RegisterIncident": {
      "Type": "Task",
      "Comment": "Register the plagiarism incident in the system and begin workflow execution.",
      "Resource": "arn:aws:lambda:us-west-2:538510314095:function:sfn-test-invoker",
      "Next": "ScheduleExam"
    },
    "ScheduleExam": {
      "Type": "Task",
      "Comment": "Set the next exam deadline for the student to complete the exam.",
      "Resource": "arn:aws:lambda:us-west-2:538510314095:function:sfn-test-invoker",
      "Next": "SendNotification",
      "Catch": [
        {
          "ErrorEquals": [
            "StudentExceededAllowableExamRetries"
          ],
          "ResultPath": "$.Error",
          "Next": "TakeAdministrativeAction"
        }
      ]
    },
    "SendNotification": {
      "Type": "Task",
      "Comment": "Send email confirming exam details and exam deadline. Wait for callback.",
      "Resource": "arn:aws:states:::lambda:invoke.waitForTaskToken",
      "Parameters":{
        "FunctionName":"SendNotificationFunction",
        "Payload":{
          "input.$":"$",
          "TaskToken.$":"$$.Task.Token"
        }
      },
      "Next": "HasStudentPassedExam"
    },
    "HasStudentPassedExam": {
      "Type": "Choice",
      "Comment": "If the student has a score less than 67, they need to reschedule",
      "Choices": [
        {
          "Variable": "$.Exams[0].Result",
          "NumericEquals": 0,
          "Next": "ResolveIncident"
        },
        {
          "Variable": "$.Exams[0].Result",
          "NumericEquals": 1,
          "Next": "ScheduleExam"
        },
        {
          "Variable": "$.Exams[0].Result",
          "NumericEquals": 2,
          "Next": "TakeAdministrativeAction"
        }
      ]
    },
    "TakeAdministrativeAction": {
      "Type": "Task",
      "Resource": "arn:aws:lambda:us-west-2:538510314095:function:sfn-test-invoker",
      "Comment": "Take administrative action if student does not sit exam or fails all three attempts.",
      "End": true
    },
    "ResolveIncident": {
      "Type": "Task",
      "Comment": "Resolves the incident for the student.",
      "End": true,
      "Resource": "arn:aws:lambda:us-west-2:538510314095:function:sfn-test-invoker"
    }
  }
}s